[{"cursor":"WyIyMDIyLTA1LTE4VDIwOjAwOjA1Ljk3N1oiLDcwMF0=","node":{"id":"auFcYh4XFygkcpzl0sEtVSITK3pZTpQTu-CDXvpSa4c","owner":{"address":"fPbQHJzvERrRLV-OqPe2LYIXFsf7TYPkEfxIsqc_9hk"},"recipient":"","bundledIn":{"id":"etsPaowFwxhYrVkGUNfCptvjZV3kNQWO9w8OoPhWh2k"},"tags":[{"name":"App-Name","value":"ArDrive-Web"},{"name":"App-Version","value":"1.16.0"},{"name":"Unix-Time","value":"1652887440"},{"name":"Content-Type","value":"application/json"}],"data":{"size":"733","type":null},"quantity":{"winston":"0"},"fee":{"winston":"0"},"block":{"timestamp":1652887724,"height":936231}}},{"cursor":"WyIyMDIyLTA1LTE4VDIwOjAwOjA1Ljk3N1oiLDcwMV0=","node":{"id":"etsPaowFwxhYrVkGUNfCptvjZV3kNQWO9w8OoPhWh2k","owner":{"address":"fPbQHJzvERrRLV-OqPe2LYIXFsf7TYPkEfxIsqc_9hk"},"recipient":"Zznp65qgTIm2QBMjjoEaHKOmQrpTu0tfOcdbkm_qoL4","bundledIn":null,"tags":[{"name":"Bundle-Format","value":"binary"},{"name":"Bundle-Version","value":"2.0.0"},{"name":"App-Name","value":"ArDrive-Web"},{"name":"App-Version","value":"1.16.0"},{"name":"Unix-Time","value":"1652887440"},{"name":"Tip-Type","value":"data upload"}],"data":{"size":"3494","type":null},"quantity":{"winston":"10794600"},"fee":{"winston":"71964004"},"block":{"timestamp":1652887724,"height":936231}}},{"cursor":"WyIyMDIyLTA1LTE4VDIwOjAwOjA1Ljk3N1oiLDcwMl0=","node":{"id":"yuAfjMU6dpJF4Bg6807tF4_uADZgFygxEUtqgN4nxMA","owner":{"address":"fPbQHJzvERrRLV-OqPe2LYIXFsf7TYPkEfxIsqc_9hk"},"recipient":"","bundledIn":{"id":"etsPaowFwxhYrVkGUNfCptvjZV3kNQWO9w8OoPhWh2k"},"tags":[{"name":"Content-Type","value":"application/json"},{"name":"ArFS","value":"0.11"},{"name":"Entity-Type","value":"file"},{"name":"Drive-Id","value":"2970f9ac-be2f-4b3a-8eaa-5bed672c04a2"},{"name":"Parent-Folder-Id","value":"78bbb2aa-0737-4352-9c4f-81b15aa13046"},{"name":"File-Id","value":"20394952-8c0e-4dd0-a164-528153829bfb"},{"name":"App-Name","value":"ArDrive-Web"},{"name":"App-Version","value":"1.16.0"},{"name":"Unix-Time","value":"1652887440"}],"data":{"size":"155","type":null},"quantity":{"winston":"0"},"fee":{"winston":"0"},"block":{"timestamp":1652887724,"height":936231}}}]