[{"cursor":"WyIyMDIyLTA1LTE1VDIyOjM1OjMzLjUxNloiLDUxMDVd","node":{"id":"ioYnJ9xTlYtnMpt5EPF6PnmdZN3KRdINTRBWkF001DI","owner":{"address":"tViV7f6Kc0Vb-3Xzr7JZ_73kLamZaLJ8yNbZBwEVTjQ"},"recipient":"","bundledIn":{"id":"QQ1CzFuNVgzkYMBm1jhTny5pfz8FAy5FsRFUEIciM1c"},"tags":[{"name":"Content-Type","value":"application/json"},{"name":"ArFS","value":"0.11"},{"name":"Entity-Type","value":"folder"},{"name":"Drive-Id","value":"3091bedd-f192-4129-9aae-467fdb0f5221"},{"name":"Folder-Id","value":"8a5bc590-a2ef-43ef-8acc-9eb32876a6f9"},{"name":"App-Name","value":"ArDrive-Web"},{"name":"App-Version","value":"1.16.0"},{"name":"Unix-Time","value":"1652518816"}],"data":{"size":"20","type":null},"quantity":{"winston":"0"},"fee":{"winston":"0"},"block":{"timestamp":1652519239,"height":933354}}},{"cursor":"WyIyMDIyLTA1LTE1VDIyOjM1OjMzLjUxNloiLDUxMDZd","node":{"id":"QQ1CzFuNVgzkYMBm1jhTny5pfz8FAy5FsRFUEIciM1c","owner":{"address":"tViV7f6Kc0Vb-3Xzr7JZ_73kLamZaLJ8yNbZBwEVTjQ"},"recipient":"","bundledIn":null,"tags":[{"name":"Bundle-Format","value":"binary"},{"name":"Bundle-Version","value":"2.0.0"},{"name":"App-Name","value":"ArDrive-Web"},{"name":"App-Version","value":"1.16.0"},{"name":"Unix-Time","value":"1652518818"}],"data":{"size":"2745","type":null},"quantity":{"winston":"0"},"fee":{"winston":"66869208"},"block":{"timestamp":1652519239,"height":933354}}},{"cursor":"WyIyMDIyLTA1LTE1VDIyOjM1OjMzLjUxNloiLDUxMDdd","node":{"id":"Zp7KdkWq9x1DubcueS1frdl5zunHPovssO1plKWHrew","owner":{"address":"tViV7f6Kc0Vb-3Xzr7JZ_73kLamZaLJ8yNbZBwEVTjQ"},"recipient":"","bundledIn":{"id":"QQ1CzFuNVgzkYMBm1jhTny5pfz8FAy5FsRFUEIciM1c"},"tags":[{"name":"Content-Type","value":"application/json"},{"name":"ArFS","value":"0.11"},{"name":"Entity-Type","value":"drive"},{"name":"Drive-Id","value":"3091bedd-f192-4129-9aae-467fdb0f5221"},{"name":"Drive-Privacy","value":"public"},{"name":"App-Name","value":"ArDrive-Web"},{"name":"App-Version","value":"1.16.0"},{"name":"Unix-Time","value":"1652518815"}],"data":{"size":"74","type":null},"quantity":{"winston":"0"},"fee":{"winston":"0"},"block":{"timestamp":1652519239,"height":933354}}}]