[{"cursor":"WyIyMDIyLTA1LTE2VDE0OjE2OjIxLjE1MloiLDkwMjk0XQ==","node":{"id":"9XOsexYRATrO46lGcu64VUJTO2XMABJzvvqL4SmsqWg","owner":{"address":"uG5qvo96rm52NMXrJgNobUGT2FRgMGnAdPBf2jXu6q0"},"recipient":"","bundledIn":{"id":"cEN4gEhqEBmD9IoDY81GAHcYZO0CfDYfleKIdfd67Hg"},"tags":[{"name":"Content-Type","value":"application/octet-stream"},{"name":"Cipher","value":"AES256-GCM"},{"name":"Cipher-IV","value":"nAUVJtIShrqREW0_"},{"name":"App-Name","value":"ArDrive-Web"},{"name":"App-Version","value":"1.13.0"},{"name":"Unix-Time","value":"1651457308"}],"data":{"size":"3908895","type":null},"quantity":{"winston":"0"},"fee":{"winston":"0"},"block":{"timestamp":1651457873,"height":925022}}},{"cursor":"WyIyMDIyLTA1LTE2VDE0OjE2OjIxLjE1MloiLDkwMjk1XQ==","node":{"id":"B6JPqxEWQcNb7UuDu03ejFFAXB0PhHdqz0WUYWrmjU8","owner":{"address":"uG5qvo96rm52NMXrJgNobUGT2FRgMGnAdPBf2jXu6q0"},"recipient":"","bundledIn":{"id":"cEN4gEhqEBmD9IoDY81GAHcYZO0CfDYfleKIdfd67Hg"},"tags":[{"name":"Content-Type","value":"application/octet-stream"},{"name":"Cipher","value":"AES256-GCM"},{"name":"Cipher-IV","value":"2r0WwetoTF3cUnD7"},{"name":"ArFS","value":"0.11"},{"name":"Entity-Type","value":"file"},{"name":"Drive-Id","value":"95cc8c17-5380-481c-8282-2f582814da9a"},{"name":"Parent-Folder-Id","value":"ed832db2-775b-4172-b12f-4967f31a7dc4"},{"name":"File-Id","value":"752ee16f-e492-460e-91a3-c58f1c977e33"},{"name":"App-Name","value":"ArDrive-Web"},{"name":"App-Version","value":"1.13.0"},{"name":"Unix-Time","value":"1651457308"}],"data":{"size":"175","type":null},"quantity":{"winston":"0"},"fee":{"winston":"0"},"block":{"timestamp":1651457873,"height":925022}}},{"cursor":"WyIyMDIyLTA1LTE2VDE0OjE2OjIxLjE1MloiLDkwMjk2XQ==","node":{"id":"cEN4gEhqEBmD9IoDY81GAHcYZO0CfDYfleKIdfd67Hg","owner":{"address":"uG5qvo96rm52NMXrJgNobUGT2FRgMGnAdPBf2jXu6q0"},"recipient":"rcO1Hi4_chcHVFBpSGOAVHVBBcljdypxlCBCbPfnu-c","bundledIn":null,"tags":[{"name":"Bundle-Format","value":"binary"},{"name":"Bundle-Version","value":"2.0.0"},{"name":"App-Name","value":"ArDrive-Web"},{"name":"App-Version","value":"1.13.0"},{"name":"Unix-Time","value":"1651457308"},{"name":"Tip-Type","value":"data upload"}],"data":{"size":"3911782","type":null},"quantity":{"winston":"134589654"},"fee":{"winston":"897264360"},"block":{"timestamp":1651457873,"height":925022}}}]