[{"cursor":"WyIyMDIyLTA1LTE2VDE0OjE2OjIxLjE1MloiLDMxMjExXQ==","node":{"id":"7HNkUTuyjr_-_pE7TuZburAruMs7Q1DUfeJu_4Uf7R8","owner":{"address":"4lbm3jUdgFctOo9lK9BfmsxAGrxbgH1B-btt-jfSGd0"},"recipient":"","bundledIn":null,"tags":[{"name":"Content-Type","value":"application/octet-stream"},{"name":"Cipher","value":"AES256-GCM"},{"name":"Cipher-IV","value":"V-j2M28vOzJC5Rj-"},{"name":"ArFS","value":"0.11"},{"name":"Entity-Type","value":"folder"},{"name":"Drive-Id","value":"48f7b46f-12d8-4dc1-ae2d-2a1c965cf442"},{"name":"Folder-Id","value":"577169bc-b956-48ab-890b-609da3ca2075"},{"name":"Parent-Folder-Id","value":"7be46f9e-bcf8-4929-9c0a-dafe467cba0f"},{"name":"App-Name","value":"ArDrive-Web"},{"name":"App-Version","value":"1.14.0"},{"name":"Unix-Time","value":"1651854545"}],"data":{"size":"41","type":"application/octet-stream"},"quantity":{"winston":"0"},"fee":{"winston":"60500712"},"block":{"timestamp":1651854877,"height":928151}}},{"cursor":"WyIyMDIyLTA1LTE2VDE0OjE2OjIxLjE1MloiLDMxMjEyXQ==","node":{"id":"b5nU8y6m9JQscXM08IJnsUp0jJbDg9P6IzmLAFXT7Es","owner":{"address":"4lbm3jUdgFctOo9lK9BfmsxAGrxbgH1B-btt-jfSGd0"},"recipient":"","bundledIn":null,"tags":[{"name":"Content-Type","value":"application/octet-stream"},{"name":"Cipher","value":"AES256-GCM"},{"name":"Cipher-IV","value":"Qd9JB4fatHdgCZSu"},{"name":"ArFS","value":"0.11"},{"name":"Entity-Type","value":"folder"},{"name":"Drive-Id","value":"48f7b46f-12d8-4dc1-ae2d-2a1c965cf442"},{"name":"Folder-Id","value":"8848d98d-f062-4992-bc55-0018d8d7622b"},{"name":"Parent-Folder-Id","value":"411f3bb8-e38c-4075-8566-5f8768d27b3c"},{"name":"App-Name","value":"ArDrive-Web"},{"name":"App-Version","value":"1.14.0"},{"name":"Unix-Time","value":"1651854600"}],"data":{"size":"37","type":"application/octet-stream"},"quantity":{"winston":"0"},"fee":{"winston":"60500712"},"block":{"timestamp":1651854877,"height":928151}}},{"cursor":"WyIyMDIyLTA1LTE2VDE0OjE2OjIxLjE1MloiLDMxMjEzXQ==","node":{"id":"dlqjiC44YqWSp3oGyBPvYa4DQgHSYVF1dP9rWLkoyVs","owner":{"address":"4lbm3jUdgFctOo9lK9BfmsxAGrxbgH1B-btt-jfSGd0"},"recipient":"","bundledIn":null,"tags":[{"name":"Content-Type","value":"application/octet-stream"},{"name":"Cipher","value":"AES256-GCM"},{"name":"Cipher-IV","value":"23OLhlVnCYcIsPXF"},{"name":"ArFS","value":"0.11"},{"name":"Entity-Type","value":"folder"},{"name":"Drive-Id","value":"48f7b46f-12d8-4dc1-ae2d-2a1c965cf442"},{"name":"Folder-Id","value":"411f3bb8-e38c-4075-8566-5f8768d27b3c"},{"name":"Parent-Folder-Id","value":"32529a9d-f259-4e58-8444-bd576571b8ac"},{"name":"App-Name","value":"ArDrive-Web"},{"name":"App-Version","value":"1.14.0"},{"name":"Unix-Time","value":"1651854584"}],"data":{"size":"41","type":"application/octet-stream"},"quantity":{"winston":"0"},"fee":{"winston":"60500712"},"block":{"timestamp":1651854877,"height":928151}}},{"cursor":"WyIyMDIyLTA1LTE2VDE0OjE2OjIxLjE1MloiLDMxMjE0XQ==","node":{"id":"jcakh9Osa9NSo-UZFTm1I0byvXin-MSuToDQ3GbWhxk","owner":{"address":"4lbm3jUdgFctOo9lK9BfmsxAGrxbgH1B-btt-jfSGd0"},"recipient":"","bundledIn":null,"tags":[{"name":"Content-Type","value":"application/octet-stream"},{"name":"Cipher","value":"AES256-GCM"},{"name":"Cipher-IV","value":"Lg2tKjVFmHfq4aKJ"},{"name":"ArFS","value":"0.11"},{"name":"Entity-Type","value":"folder"},{"name":"Drive-Id","value":"48f7b46f-12d8-4dc1-ae2d-2a1c965cf442"},{"name":"Folder-Id","value":"040b8fc7-05b5-4abf-8e6e-58d5e461ab07"},{"name":"Parent-Folder-Id","value":"7be46f9e-bcf8-4929-9c0a-dafe467cba0f"},{"name":"App-Name","value":"ArDrive-Web"},{"name":"App-Version","value":"1.14.0"},{"name":"Unix-Time","value":"1651854528"}],"data":{"size":"36","type":"application/octet-stream"},"quantity":{"winston":"0"},"fee":{"winston":"60500712"},"block":{"timestamp":1651854877,"height":928151}}},{"cursor":"WyIyMDIyLTA1LTE2VDE0OjE2OjIxLjE1MloiLDMxMjE1XQ==","node":{"id":"V9FBFDnc3kNivVeVkejCY0QpwPm-j1d1zUZ6P22WqBw","owner":{"address":"4lbm3jUdgFctOo9lK9BfmsxAGrxbgH1B-btt-jfSGd0"},"recipient":"","bundledIn":null,"tags":[{"name":"Content-Type","value":"application/octet-stream"},{"name":"Cipher","value":"AES256-GCM"},{"name":"Cipher-IV","value":"nVhhf1mfGZzL-ScY"},{"name":"ArFS","value":"0.11"},{"name":"Entity-Type","value":"folder"},{"name":"Drive-Id","value":"48f7b46f-12d8-4dc1-ae2d-2a1c965cf442"},{"name":"Folder-Id","value":"37bb0310-ce63-412d-b8fa-939e04d8670f"},{"name":"Parent-Folder-Id","value":"7be46f9e-bcf8-4929-9c0a-dafe467cba0f"},{"name":"App-Name","value":"ArDrive-Web"},{"name":"App-Version","value":"1.14.0"},{"name":"Unix-Time","value":"1651854558"}],"data":{"size":"39","type":"application/octet-stream"},"quantity":{"winston":"0"},"fee":{"winston":"60500712"},"block":{"timestamp":1651854877,"height":928151}}}]