[{"cursor":"WyIyMDIyLTA1LTE2VDE0OjE2OjIxLjE1MloiLDgzNTI4XQ==","node":{"id":"7QIF8UJ-BAlkhGucz1htQYxbMx-LAQEceZ1jY0NFxCg","owner":{"address":"Tp3S06bDSnQDA601rYb7zXK1RTYwFNsGFfpYIKDFyXA"},"recipient":"Zznp65qgTIm2QBMjjoEaHKOmQrpTu0tfOcdbkm_qoL4","bundledIn":null,"tags":[{"name":"Bundle-Format","value":"binary"},{"name":"Bundle-Version","value":"2.0.0"},{"name":"App-Name","value":"ArDrive-Web"},{"name":"App-Version","value":"1.13.0"},{"name":"Unix-Time","value":"1651560907"},{"name":"Tip-Type","value":"data upload"}],"data":{"size":"409062","type":null},"quantity":{"winston":"18420230"},"fee":{"winston":"122801534"},"block":{"timestamp":1651561543,"height":925830}}},{"cursor":"WyIyMDIyLTA1LTE2VDE0OjE2OjIxLjE1MloiLDgzNTI5XQ==","node":{"id":"MPFOeCbHkZuNb4Sxbixl8mrGV7kAkY8vHKVSI2qPSGk","owner":{"address":"Tp3S06bDSnQDA601rYb7zXK1RTYwFNsGFfpYIKDFyXA"},"recipient":"","bundledIn":{"id":"7QIF8UJ-BAlkhGucz1htQYxbMx-LAQEceZ1jY0NFxCg"},"tags":[{"name":"Content-Type","value":"application/octet-stream"},{"name":"Cipher","value":"AES256-GCM"},{"name":"Cipher-IV","value":"vQxKSwa_paFt9ghg"},{"name":"ArFS","value":"0.11"},{"name":"Entity-Type","value":"file"},{"name":"Drive-Id","value":"abbc5e19-73bb-48c2-8b39-074d92cf118f"},{"name":"Parent-Folder-Id","value":"2f3e913e-d86b-4c91-8ab9-e6ca60348bb8"},{"name":"File-Id","value":"498894df-6178-46b4-82e6-ffc5b2f59099"},{"name":"App-Name","value":"ArDrive-Web"},{"name":"App-Version","value":"1.13.0"},{"name":"Unix-Time","value":"1651560907"}],"data":{"size":"186","type":null},"quantity":{"winston":"0"},"fee":{"winston":"0"},"block":{"timestamp":1651561543,"height":925830}}},{"cursor":"WyIyMDIyLTA1LTE2VDE0OjE2OjIxLjE1MloiLDgzNTMwXQ==","node":{"id":"TaN0UoMflkVHpzD1-pp56JTa3kdZrJZXey0O9yLMKfo","owner":{"address":"Tp3S06bDSnQDA601rYb7zXK1RTYwFNsGFfpYIKDFyXA"},"recipient":"","bundledIn":{"id":"7QIF8UJ-BAlkhGucz1htQYxbMx-LAQEceZ1jY0NFxCg"},"tags":[{"name":"Content-Type","value":"application/octet-stream"},{"name":"Cipher","value":"AES256-GCM"},{"name":"Cipher-IV","value":"zAedqH-71xke6_5R"},{"name":"App-Name","value":"ArDrive-Web"},{"name":"App-Version","value":"1.13.0"},{"name":"Unix-Time","value":"1651560907"}],"data":{"size":"406164","type":null},"quantity":{"winston":"0"},"fee":{"winston":"0"},"block":{"timestamp":1651561543,"height":925830}}}]