[{"cursor":"WyIyMDIyLTA1LTE2VDE0OjE2OjIxLjE1MloiLDI3MTg3XQ==","node":{"id":"DpMMyhmyVp-39r5z9hp9E92NQ2MaCZ_QTZ9qtsi-e5M","owner":{"address":"8giprWA7Y6wxvcEPh6ThxJ-31-fYTnsvuSFIY5fXt8Q"},"recipient":"","bundledIn":null,"tags":[{"name":"App-Name","value":"ArDrive-CLI"},{"name":"App-Version","value":"1.5.0"},{"name":"ArFS","value":"0.11"},{"name":"Content-Type","value":"application/json"},{"name":"Entity-Type","value":"file"},{"name":"Unix-Time","value":"1651875298"},{"name":"Drive-Id","value":"490852a6-2cdf-4d6d-bdb3-c32b6ae6737d"},{"name":"File-Id","value":"a741dd42-4679-4316-b5b8-ea0d2609b0f3"},{"name":"Parent-Folder-Id","value":"dd3cb7ef-7008-44a9-b24f-fe6d0d18bac2"}],"data":{"size":"152","type":"application/json"},"quantity":{"winston":"0"},"fee":{"winston":"60500712"},"block":{"timestamp":1651876995,"height":928331}}},{"cursor":"WyIyMDIyLTA1LTE2VDE0OjE2OjIxLjE1MloiLDI3MTg4XQ==","node":{"id":"Pgfbvp1BiKi4YIAuZtfZMz9nytnCQaP1MUpJSkFh9GM","owner":{"address":"8giprWA7Y6wxvcEPh6ThxJ-31-fYTnsvuSFIY5fXt8Q"},"recipient":"","bundledIn":null,"tags":[{"name":"App-Name","value":"ArDrive-CLI"},{"name":"App-Version","value":"1.5.0"},{"name":"ArFS","value":"0.11"},{"name":"Content-Type","value":"application/json"},{"name":"Entity-Type","value":"file"},{"name":"Unix-Time","value":"1651875302"},{"name":"Drive-Id","value":"490852a6-2cdf-4d6d-bdb3-c32b6ae6737d"},{"name":"File-Id","value":"3617574b-e544-4053-bcb3-f710bd37a3df"},{"name":"Parent-Folder-Id","value":"dd3cb7ef-7008-44a9-b24f-fe6d0d18bac2"}],"data":{"size":"152","type":"application/json"},"quantity":{"winston":"0"},"fee":{"winston":"60500712"},"block":{"timestamp":1651876995,"height":928331}}},{"cursor":"WyIyMDIyLTA1LTE2VDE0OjE2OjIxLjE1MloiLDI3MTg5XQ==","node":{"id":"U5l8LRljQJt03PqzS-28gW4u1Wl-yJMgdqZsFl7n96M","owner":{"address":"8giprWA7Y6wxvcEPh6ThxJ-31-fYTnsvuSFIY5fXt8Q"},"recipient":"","bundledIn":null,"tags":[{"name":"App-Name","value":"ArDrive-CLI"},{"name":"App-Version","value":"1.5.0"},{"name":"ArFS","value":"0.11"},{"name":"Content-Type","value":"application/json"},{"name":"Entity-Type","value":"file"},{"name":"Unix-Time","value":"1651875318"},{"name":"Drive-Id","value":"490852a6-2cdf-4d6d-bdb3-c32b6ae6737d"},{"name":"File-Id","value":"6d39738b-90a3-4b5d-b6fa-ad9380e748b5"},{"name":"Parent-Folder-Id","value":"dd3cb7ef-7008-44a9-b24f-fe6d0d18bac2"}],"data":{"size":"152","type":"application/json"},"quantity":{"winston":"0"},"fee":{"winston":"60500712"},"block":{"timestamp":1651876995,"height":928331}}},{"cursor":"WyIyMDIyLTA1LTE2VDE0OjE2OjIxLjE1MloiLDI3MTkwXQ==","node":{"id":"vE5I5EWtRgq4dVSQqmJmXFY5xX4SBDOFO9KWrQOzEVM","owner":{"address":"8giprWA7Y6wxvcEPh6ThxJ-31-fYTnsvuSFIY5fXt8Q"},"recipient":"","bundledIn":null,"tags":[{"name":"App-Name","value":"ArDrive-CLI"},{"name":"App-Version","value":"1.5.0"},{"name":"ArFS","value":"0.11"},{"name":"Content-Type","value":"application/json"},{"name":"Entity-Type","value":"file"},{"name":"Unix-Time","value":"1651875301"},{"name":"Drive-Id","value":"490852a6-2cdf-4d6d-bdb3-c32b6ae6737d"},{"name":"File-Id","value":"58a3a819-ce4a-4a7e-9bfa-bab207095490"},{"name":"Parent-Folder-Id","value":"dd3cb7ef-7008-44a9-b24f-fe6d0d18bac2"}],"data":{"size":"153","type":"application/json"},"quantity":{"winston":"0"},"fee":{"winston":"60500712"},"block":{"timestamp":1651876995,"height":928331}}}]