[{"cursor":"WyIyMDIyLTA1LTE1VDIyOjM1OjMzLjUxNloiLDExNjkwN10=","node":{"id":"09T0c8VN1w5hZZcEnUOe84rP0MVsvpQDvb0ED61w9Zk","owner":{"address":"dHxZZQ3GHLgxgzVKbuiwE6wl-atqgScJvVJg81v9gro"},"recipient":"Zznp65qgTIm2QBMjjoEaHKOmQrpTu0tfOcdbkm_qoL4","bundledIn":null,"tags":[{"name":"Bundle-Format","value":"binary"},{"name":"Bundle-Version","value":"2.0.0"},{"name":"App-Name","value":"ArDrive-Web"},{"name":"App-Version","value":"1.14.1"},{"name":"Unix-Time","value":"1652278022"},{"name":"Tip-Type","value":"data upload"}],"data":{"size":"935255","type":null},"quantity":{"winston":"36728367"},"fee":{"winston":"244855780"},"block":{"timestamp":1652278619,"height":931490}}},{"cursor":"WyIyMDIyLTA1LTE1VDIyOjM1OjMzLjUxNloiLDExNjkwOF0=","node":{"id":"ZqKlfarsDEBxWMOBAWUL8AjNBZ36gU_2BJ5QAPDvlCk","owner":{"address":"dHxZZQ3GHLgxgzVKbuiwE6wl-atqgScJvVJg81v9gro"},"recipient":"Zznp65qgTIm2QBMjjoEaHKOmQrpTu0tfOcdbkm_qoL4","bundledIn":null,"tags":[{"name":"Bundle-Format","value":"binary"},{"name":"Bundle-Version","value":"2.0.0"},{"name":"App-Name","value":"ArDrive-Web"},{"name":"App-Version","value":"1.14.1"},{"name":"Unix-Time","value":"1652278335"},{"name":"Tip-Type","value":"data upload"}],"data":{"size":"935255","type":null},"quantity":{"winston":"36728367"},"fee":{"winston":"244855780"},"block":{"timestamp":1652278619,"height":931490}}}]