[{"cursor":"WyIyMDIyLTA1LTE1VDIyOjM1OjMzLjUxNloiLDExNjg5NF0=","node":{"id":"dDQxDFfUdUVwfgeS7jlFgyMhyCPFQq6omVdFOiNFe_4","owner":{"address":"Ym4bGOsfnN1XI5tY_ccQyCl-xyqT68K2QaCwxCNDWp0"},"recipient":"","bundledIn":null,"tags":[{"name":"App-Name","value":"ArDrive-Core"},{"name":"App-Version","value":"1.13.0-alpha-0"},{"name":"ArFS","value":"0.11"},{"name":"Content-Type","value":"application/json"},{"name":"Entity-Type","value":"folder"},{"name":"Unix-Time","value":"1652281105"},{"name":"Drive-Id","value":"15499cae-019c-459e-8587-099c45fb0e7b"},{"name":"Folder-Id","value":"edb6acf3-83a1-4228-9941-8cc4180ee7b3"},{"name":"Parent-Folder-Id","value":"74e23e29-a383-4cdb-a8ba-8926b7f3dd0f"}],"data":{"size":"35","type":"application/json"},"quantity":{"winston":"0"},"fee":{"winston":"61774411"},"block":{"timestamp":1652281296,"height":931512}}}]