[{"cursor":"WyIyMDIyLTA1LTIwVDE3OjU1OjAzLjk0MVoiLDU0Nzld","node":{"id":"oSXiW8o8yTjire1__skEqc7IYa7FEfmy5ydGf-bXWEQ","owner":{"address":"yBaySP5IZWB4dRoFBXLBKJZmaefdk-chxf2eMdtYClY"},"recipient":"","bundledIn":null,"tags":[{"name":"Content-Type","value":"application/json"},{"name":"ArFS","value":"0.11"},{"name":"Entity-Type","value":"folder"},{"name":"Drive-Id","value":"3dae2265-aefe-45cb-842a-6c39c0f98bec"},{"name":"Folder-Id","value":"535cc0a5-c84a-4538-ae80-5325040b70b3"},{"name":"Parent-Folder-Id","value":"e26953cb-d982-4dd1-8cdb-d3a374839ae6"},{"name":"App-Name","value":"ArDrive-Web"},{"name":"App-Version","value":"1.17.0"},{"name":"Unix-Time","value":"1653011758"}],"data":{"size":"19","type":"application/json"},"quantity":{"winston":"0"},"fee":{"winston":"73237704"},"block":{"timestamp":1653011904,"height":937201}}}]