[{"cursor":"WyIyMDIyLTA1LTE1VDIyOjM1OjMzLjUxNloiLDYzMTdd","node":{"id":"AiTXminw1rTFn43e6d9Uj846csJMUASQc3nz9SHkg8o","owner":{"address":"ve9PyM3WEkCMIuGT_3kp3Cr0TRIYUfx-O3sirL13BDs"},"recipient":"","bundledIn":{"id":"M44S00183hKYKGwK9yWPFIM34hCkTfyqVBJfRTOWoQ0"},"tags":[{"name":"App-Name","value":"ArDrive-Web"},{"name":"App-Version","value":"1.16.0"},{"name":"Unix-Time","value":"1652477045"},{"name":"Content-Type","value":"application/json"}],"data":{"size":"193","type":null},"quantity":{"winston":"0"},"fee":{"winston":"0"},"block":{"timestamp":1652477101,"height":933029}}},{"cursor":"WyIyMDIyLTA1LTE1VDIyOjM1OjMzLjUxNloiLDYzMThd","node":{"id":"knJqX3cJDF23mHP-lt1PX7TMpkE7Z1L8vHgmo85RSl0","owner":{"address":"ve9PyM3WEkCMIuGT_3kp3Cr0TRIYUfx-O3sirL13BDs"},"recipient":"","bundledIn":{"id":"M44S00183hKYKGwK9yWPFIM34hCkTfyqVBJfRTOWoQ0"},"tags":[{"name":"Content-Type","value":"application/json"},{"name":"ArFS","value":"0.11"},{"name":"Entity-Type","value":"file"},{"name":"Drive-Id","value":"2c14550a-9fcf-4f29-88c9-bf8e5316377c"},{"name":"Parent-Folder-Id","value":"8be5309f-7b0b-4424-bf96-ef278e9dd291"},{"name":"File-Id","value":"911990b9-a0da-4b70-b056-5cea0db1b281"},{"name":"App-Name","value":"ArDrive-Web"},{"name":"App-Version","value":"1.16.0"},{"name":"Unix-Time","value":"1652477045"}],"data":{"size":"160","type":null},"quantity":{"winston":"0"},"fee":{"winston":"0"},"block":{"timestamp":1652477101,"height":933029}}},{"cursor":"WyIyMDIyLTA1LTE1VDIyOjM1OjMzLjUxNloiLDYzMTld","node":{"id":"M44S00183hKYKGwK9yWPFIM34hCkTfyqVBJfRTOWoQ0","owner":{"address":"ve9PyM3WEkCMIuGT_3kp3Cr0TRIYUfx-O3sirL13BDs"},"recipient":"aoaJNC8NcKVfgwaUj6kyJi2hKrVGUsRHCGf8RhKnsic","bundledIn":null,"tags":[{"name":"Bundle-Format","value":"binary"},{"name":"Bundle-Version","value":"2.0.0"},{"name":"App-Name","value":"ArDrive-Web"},{"name":"App-Version","value":"1.16.0"},{"name":"Unix-Time","value":"1652477045"},{"name":"Tip-Type","value":"data upload"}],"data":{"size":"2959","type":null},"quantity":{"winston":"10000000"},"fee":{"winston":"64958659"},"block":{"timestamp":1652477101,"height":933029}}}]