[{"cursor":"WyIyMDIyLTA1LTE2VDE0OjE2OjIxLjE1MloiLDkwNDIxXQ==","node":{"id":"dfvUoypWkwuAlnHH--qfnHZrbhl9YeuZcWRIjeKPWO0","owner":{"address":"M2CR_Eow6ocqTe7Ji3hRi1uhWDCkwxtckpso8Pp47lM"},"recipient":"-OtTqVqAGqTBzhviZptnUTys7rWenNrnQcjGtvDBDdo","bundledIn":null,"tags":[{"name":"Bundle-Format","value":"binary"},{"name":"Bundle-Version","value":"2.0.0"},{"name":"App-Name","value":"ArDrive-Web"},{"name":"App-Version","value":"1.14.0"},{"name":"Unix-Time","value":"1651441229"},{"name":"Tip-Type","value":"data upload"}],"data":{"size":"426457371","type":null},"quantity":{"winston":"14433149092"},"fee":{"winston":"96220993948"},"block":{"timestamp":1651441657,"height":924893}}}]