[{"cursor":"WyIyMDIyLTA1LTE2VDE0OjE2OjIxLjE1MloiLDI3MzY3XQ==","node":{"id":"C6gx3IifP3lKEIOyIC4_ZaxOwMtUfN-_1K_ra-GfJMs","owner":{"address":"APu-o6jP4A-guGvE1UVUIYGfP1d366e07iWv4ftYhNo"},"recipient":"DtTSW9Sua_LjzZlImC4QbcHw3dow6duMh2mfEOCSf70","bundledIn":null,"tags":[{"name":"Bundle-Format","value":"binary"},{"name":"Bundle-Version","value":"2.0.0"},{"name":"App-Name","value":"ArDrive-Web"},{"name":"App-Version","value":"1.14.1"},{"name":"Unix-Time","value":"1651873357"},{"name":"Tip-Type","value":"data upload"}],"data":{"size":"1077867","type":null},"quantity":{"winston":"44936406"},"fee":{"winston":"299576040"},"block":{"timestamp":1651873962,"height":928299}}},{"cursor":"WyIyMDIyLTA1LTE2VDE0OjE2OjIxLjE1MloiLDI3MzY4XQ==","node":{"id":"h48ZVhPquwlIgIki08BSFmVaqg4Q2KZJ7FHuwl6YGyw","owner":{"address":"8giprWA7Y6wxvcEPh6ThxJ-31-fYTnsvuSFIY5fXt8Q"},"recipient":"Zznp65qgTIm2QBMjjoEaHKOmQrpTu0tfOcdbkm_qoL4","bundledIn":null,"tags":[{"name":"App-Name","value":"ArDrive-CLI"},{"name":"App-Version","value":"1.5.0"},{"name":"Type","value":"fee"},{"name":"Tip-Type","value":"data upload"}],"data":{"size":"0","type":null},"quantity":{"winston":"27005756"},"fee":{"winston":"731880"},"block":{"timestamp":1651873962,"height":928299}}},{"cursor":"WyIyMDIyLTA1LTE2VDE0OjE2OjIxLjE1MloiLDI3MzY5XQ==","node":{"id":"mHs2jmZXD6XsJcS35YlBwwCOsMTUv4wksScYIQ0LSCg","owner":{"address":"APu-o6jP4A-guGvE1UVUIYGfP1d366e07iWv4ftYhNo"},"recipient":"","bundledIn":{"id":"C6gx3IifP3lKEIOyIC4_ZaxOwMtUfN-_1K_ra-GfJMs"},"tags":[{"name":"Content-Type","value":"application/octet-stream"},{"name":"Cipher","value":"AES256-GCM"},{"name":"Cipher-IV","value":"8tzLp5MrZdEC2XNH"},{"name":"App-Name","value":"ArDrive-Web"},{"name":"App-Version","value":"1.14.1"},{"name":"Unix-Time","value":"1651873354"}],"data":{"size":"1074955","type":null},"quantity":{"winston":"0"},"fee":{"winston":"0"},"block":{"timestamp":1651873962,"height":928299}}},{"cursor":"WyIyMDIyLTA1LTE2VDE0OjE2OjIxLjE1MloiLDI3MzcwXQ==","node":{"id":"Mrqb859IQsU2VuFR-lsZw4yc7tx_seuc5S9F7SrPN8k","owner":{"address":"8giprWA7Y6wxvcEPh6ThxJ-31-fYTnsvuSFIY5fXt8Q"},"recipient":"","bundledIn":null,"tags":[{"name":"App-Name","value":"ArDrive-CLI"},{"name":"App-Version","value":"1.5.0"},{"name":"ArFS","value":"0.11"},{"name":"Content-Type","value":"application/json"},{"name":"Entity-Type","value":"file"},{"name":"Unix-Time","value":"1651873029"},{"name":"Drive-Id","value":"490852a6-2cdf-4d6d-bdb3-c32b6ae6737d"},{"name":"File-Id","value":"a5189d7e-3ef9-45ee-9a56-c598bb19619f"},{"name":"Parent-Folder-Id","value":"dd3cb7ef-7008-44a9-b24f-fe6d0d18bac2"}],"data":{"size":"152","type":"application/json"},"quantity":{"winston":"0"},"fee":{"winston":"60500712"},"block":{"timestamp":1651873962,"height":928299}}},{"cursor":"WyIyMDIyLTA1LTE2VDE0OjE2OjIxLjE1MloiLDI3MzcxXQ==","node":{"id":"qkcIZO7v8ICadv24kbtkKsW0kcRsbUsYPTbuQ4M6RMI","owner":{"address":"8giprWA7Y6wxvcEPh6ThxJ-31-fYTnsvuSFIY5fXt8Q"},"recipient":"","bundledIn":null,"tags":[{"name":"App-Name","value":"ArDrive-CLI"},{"name":"App-Version","value":"1.5.0"},{"name":"ArFS","value":"0.11"},{"name":"Content-Type","value":"application/json"},{"name":"Entity-Type","value":"file"},{"name":"Unix-Time","value":"1651873002"},{"name":"Drive-Id","value":"490852a6-2cdf-4d6d-bdb3-c32b6ae6737d"},{"name":"File-Id","value":"16d7fa72-2ea4-4fff-86f7-d7b76849269b"},{"name":"Parent-Folder-Id","value":"dd3cb7ef-7008-44a9-b24f-fe6d0d18bac2"}],"data":{"size":"152","type":"application/json"},"quantity":{"winston":"0"},"fee":{"winston":"60500712"},"block":{"timestamp":1651873962,"height":928299}}},{"cursor":"WyIyMDIyLTA1LTE2VDE0OjE2OjIxLjE1MloiLDI3MzcyXQ==","node":{"id":"wdJuTK6JLQudfwMP8MrSlOvJt5XcglmxoBJhl_joeKM","owner":{"address":"8giprWA7Y6wxvcEPh6ThxJ-31-fYTnsvuSFIY5fXt8Q"},"recipient":"pcXbai9GoRbtBWrAgb8RkyEuDXYy5DBn0rMNfg6azGg","bundledIn":null,"tags":[{"name":"App-Name","value":"ArDrive-CLI"},{"name":"App-Version","value":"1.5.0"},{"name":"Type","value":"fee"},{"name":"Tip-Type","value":"data upload"}],"data":{"size":"0","type":null},"quantity":{"winston":"27005756"},"fee":{"winston":"731880"},"block":{"timestamp":1651873962,"height":928299}}},{"cursor":"WyIyMDIyLTA1LTE2VDE0OjE2OjIxLjE1MloiLDI3MzczXQ==","node":{"id":"YTeWVYRt_AMzMKETlE9gCHTI9l3j82RnmhdXQpBd64A","owner":{"address":"APu-o6jP4A-guGvE1UVUIYGfP1d366e07iWv4ftYhNo"},"recipient":"","bundledIn":{"id":"C6gx3IifP3lKEIOyIC4_ZaxOwMtUfN-_1K_ra-GfJMs"},"tags":[{"name":"Content-Type","value":"application/octet-stream"},{"name":"Cipher","value":"AES256-GCM"},{"name":"Cipher-IV","value":"NZM7qRF4QK-28ieg"},{"name":"ArFS","value":"0.11"},{"name":"Entity-Type","value":"file"},{"name":"Drive-Id","value":"f3d9ace9-7350-4d70-bd58-a029e9d2b0f7"},{"name":"Parent-Folder-Id","value":"a0306019-b5ef-401d-b148-5cd10244e17f"},{"name":"File-Id","value":"82ed9693-ffac-410f-80b2-c4bcffc31ca6"},{"name":"App-Name","value":"ArDrive-Web"},{"name":"App-Version","value":"1.14.1"},{"name":"Unix-Time","value":"1651873355"}],"data":{"size":"200","type":null},"quantity":{"winston":"0"},"fee":{"winston":"0"},"block":{"timestamp":1651873962,"height":928299}}},{"cursor":"WyIyMDIyLTA1LTE2VDE0OjE2OjIxLjE1MloiLDI3Mzc0XQ==","node":{"id":"ZsI6VYxjNHMsvsSONNHY1BOkE9HeRoEKwT1keaAN8kM","owner":{"address":"8giprWA7Y6wxvcEPh6ThxJ-31-fYTnsvuSFIY5fXt8Q"},"recipient":"Zznp65qgTIm2QBMjjoEaHKOmQrpTu0tfOcdbkm_qoL4","bundledIn":null,"tags":[{"name":"App-Name","value":"ArDrive-CLI"},{"name":"App-Version","value":"1.5.0"},{"name":"Type","value":"fee"},{"name":"Tip-Type","value":"data upload"}],"data":{"size":"0","type":null},"quantity":{"winston":"27005756"},"fee":{"winston":"731880"},"block":{"timestamp":1651873962,"height":928299}}}]