[{"cursor":"WyIyMDIyLTA1LTE5VDIwOjUyOjE0LjY1NloiLDdd","node":{"id":"d6k4MgzHmt5Z4FW7w32E7JKFOROxewSVG4fWwrQBB4E","owner":{"address":"APu-o6jP4A-guGvE1UVUIYGfP1d366e07iWv4ftYhNo"},"recipient":"","bundledIn":{"id":"x00vITM8PAN8Xy6glFkU32a94s3cBlIEMSzpmoTt3KU"},"tags":[{"name":"Content-Type","value":"application/octet-stream"},{"name":"Cipher","value":"AES256-GCM"},{"name":"Cipher-IV","value":"hEIMveoXCOm4HkM8"},{"name":"App-Name","value":"ArDrive-Web"},{"name":"App-Version","value":"1.17.0"},{"name":"Unix-Time","value":"1652992157"}],"data":{"size":"528","type":null},"quantity":{"winston":"0"},"fee":{"winston":"0"},"block":{"timestamp":1652992299,"height":937045}}},{"cursor":"WyIyMDIyLTA1LTE5VDIwOjUyOjE0LjY1NloiLDhd","node":{"id":"syUtzL5A4_jkKF1FJPQO6R6mFKOhPwdQGg4FT4oP1CA","owner":{"address":"APu-o6jP4A-guGvE1UVUIYGfP1d366e07iWv4ftYhNo"},"recipient":"","bundledIn":{"id":"x00vITM8PAN8Xy6glFkU32a94s3cBlIEMSzpmoTt3KU"},"tags":[{"name":"Content-Type","value":"application/octet-stream"},{"name":"Cipher","value":"AES256-GCM"},{"name":"Cipher-IV","value":"X_KTDYHXL4Oe3ATp"},{"name":"ArFS","value":"0.11"},{"name":"Entity-Type","value":"file"},{"name":"Drive-Id","value":"f3d9ace9-7350-4d70-bd58-a029e9d2b0f7"},{"name":"Parent-Folder-Id","value":"8ef68a86-536b-4f8b-999e-f1d018632017"},{"name":"File-Id","value":"0e9baccd-6c99-420e-a3d4-3d24e9a60be4"},{"name":"App-Name","value":"ArDrive-Web"},{"name":"App-Version","value":"1.17.0"},{"name":"Unix-Time","value":"1652992157"}],"data":{"size":"181","type":null},"quantity":{"winston":"0"},"fee":{"winston":"0"},"block":{"timestamp":1652992299,"height":937045}}},{"cursor":"WyIyMDIyLTA1LTE5VDIwOjUyOjE0LjY1NloiLDld","node":{"id":"x00vITM8PAN8Xy6glFkU32a94s3cBlIEMSzpmoTt3KU","owner":{"address":"APu-o6jP4A-guGvE1UVUIYGfP1d366e07iWv4ftYhNo"},"recipient":"i325n3L2UvgcavEM8UnFfY0OWBiyf2RrbNsLStPI73o","bundledIn":null,"tags":[{"name":"Bundle-Format","value":"binary"},{"name":"Bundle-Version","value":"2.0.0"},{"name":"App-Name","value":"ArDrive-Web"},{"name":"App-Version","value":"1.17.0"},{"name":"Unix-Time","value":"1652992157"},{"name":"Tip-Type","value":"data upload"}],"data":{"size":"3421","type":null},"quantity":{"winston":"10890128"},"fee":{"winston":"72600854"},"block":{"timestamp":1652992299,"height":937045}}}]