[{"cursor":"WyIyMDIyLTA1LTE2VDE0OjE2OjIxLjE1MloiLDc1OTcwXQ==","node":{"id":"72EKNhYkJfyOcaCNqylYFBxi4AwbFu3ayWSeHX9huNg","owner":{"address":"Shu_0sBFhXRcRcVXGiSE8IvduPRBnoPKK85IG3AKVAc"},"recipient":"","bundledIn":{"id":"rt8YCWKGL64hqeKsoXJlJwBtZgiYs2prLwDqVEU2qSM"},"tags":[{"name":"Content-Type","value":"application/octet-stream"},{"name":"Cipher","value":"AES256-GCM"},{"name":"Cipher-IV","value":"h10uNjLN0UhtJkK_"},{"name":"ArFS","value":"0.11"},{"name":"Entity-Type","value":"folder"},{"name":"Drive-Id","value":"07f88d70-4200-4404-86eb-056b72cb1b18"},{"name":"Folder-Id","value":"6b372496-8cd2-4b60-99bf-c8837c2d864d"},{"name":"Parent-Folder-Id","value":"96c26a9b-d6ba-449c-b6c7-aac2a799b0cd"},{"name":"App-Name","value":"ArDrive-Web"},{"name":"App-Version","value":"1.14.0"},{"name":"Unix-Time","value":"1651720170"}],"data":{"size":"29","type":null},"quantity":{"winston":"0"},"fee":{"winston":"0"},"block":{"timestamp":1651721102,"height":927097}}},{"cursor":"WyIyMDIyLTA1LTE2VDE0OjE2OjIxLjE1MloiLDc1OTcxXQ==","node":{"id":"Abm7okuM6O8n99tZ3t6-Vt4HOGYbIdm-wBFKvW2M6fc","owner":{"address":"Shu_0sBFhXRcRcVXGiSE8IvduPRBnoPKK85IG3AKVAc"},"recipient":"","bundledIn":{"id":"rt8YCWKGL64hqeKsoXJlJwBtZgiYs2prLwDqVEU2qSM"},"tags":[{"name":"Content-Type","value":"application/octet-stream"},{"name":"Cipher","value":"AES256-GCM"},{"name":"Cipher-IV","value":"6tCE6fRK3LsFAJ5-"},{"name":"App-Name","value":"ArDrive-Web"},{"name":"App-Version","value":"1.14.0"},{"name":"Unix-Time","value":"1651720521"}],"data":{"size":"37161362","type":null},"quantity":{"winston":"0"},"fee":{"winston":"0"},"block":{"timestamp":1651721102,"height":927097}}},{"cursor":"WyIyMDIyLTA1LTE2VDE0OjE2OjIxLjE1MloiLDc1OTcyXQ==","node":{"id":"BeT6Ag9Ru2dchVv_ZaCIDOGbHNgkUgMHq10YnU6xxZo","owner":{"address":"Shu_0sBFhXRcRcVXGiSE8IvduPRBnoPKK85IG3AKVAc"},"recipient":"","bundledIn":{"id":"rt8YCWKGL64hqeKsoXJlJwBtZgiYs2prLwDqVEU2qSM"},"tags":[{"name":"Content-Type","value":"application/octet-stream"},{"name":"Cipher","value":"AES256-GCM"},{"name":"Cipher-IV","value":"dnI2F-ePOHDHoCNI"},{"name":"App-Name","value":"ArDrive-Web"},{"name":"App-Version","value":"1.14.0"},{"name":"Unix-Time","value":"1651720508"}],"data":{"size":"36999327","type":null},"quantity":{"winston":"0"},"fee":{"winston":"0"},"block":{"timestamp":1651721102,"height":927097}}},{"cursor":"WyIyMDIyLTA1LTE2VDE0OjE2OjIxLjE1MloiLDc1OTczXQ==","node":{"id":"cED5sqBITmX5v6CAnRxSTwwPETuMsMPfmFNJKA21_eY","owner":{"address":"Shu_0sBFhXRcRcVXGiSE8IvduPRBnoPKK85IG3AKVAc"},"recipient":"","bundledIn":{"id":"rt8YCWKGL64hqeKsoXJlJwBtZgiYs2prLwDqVEU2qSM"},"tags":[{"name":"Content-Type","value":"application/octet-stream"},{"name":"Cipher","value":"AES256-GCM"},{"name":"Cipher-IV","value":"VK0zCT5Z7HCIhuLZ"},{"name":"ArFS","value":"0.11"},{"name":"Entity-Type","value":"file"},{"name":"Drive-Id","value":"07f88d70-4200-4404-86eb-056b72cb1b18"},{"name":"Parent-Folder-Id","value":"6b372496-8cd2-4b60-99bf-c8837c2d864d"},{"name":"File-Id","value":"48e01c23-d67a-44b7-993d-7bac64ec1af6"},{"name":"App-Name","value":"ArDrive-Web"},{"name":"App-Version","value":"1.14.0"},{"name":"Unix-Time","value":"1651720544"}],"data":{"size":"188","type":null},"quantity":{"winston":"0"},"fee":{"winston":"0"},"block":{"timestamp":1651721102,"height":927097}}},{"cursor":"WyIyMDIyLTA1LTE2VDE0OjE2OjIxLjE1MloiLDc1OTc0XQ==","node":{"id":"-CQGtfgX1IbNWaOz8fjv0GWOeV9cVF7bl4RRlZM_HNI","owner":{"address":"Shu_0sBFhXRcRcVXGiSE8IvduPRBnoPKK85IG3AKVAc"},"recipient":"","bundledIn":{"id":"rt8YCWKGL64hqeKsoXJlJwBtZgiYs2prLwDqVEU2qSM"},"tags":[{"name":"Content-Type","value":"application/octet-stream"},{"name":"Cipher","value":"AES256-GCM"},{"name":"Cipher-IV","value":"Tbyp_naZOF6mv8FA"},{"name":"ArFS","value":"0.11"},{"name":"Entity-Type","value":"file"},{"name":"Drive-Id","value":"07f88d70-4200-4404-86eb-056b72cb1b18"},{"name":"Parent-Folder-Id","value":"6b372496-8cd2-4b60-99bf-c8837c2d864d"},{"name":"File-Id","value":"a880e851-cf46-446f-9848-8b93739d407d"},{"name":"App-Name","value":"ArDrive-Web"},{"name":"App-Version","value":"1.14.0"},{"name":"Unix-Time","value":"1651720544"}],"data":{"size":"188","type":null},"quantity":{"winston":"0"},"fee":{"winston":"0"},"block":{"timestamp":1651721102,"height":927097}}},{"cursor":"WyIyMDIyLTA1LTE2VDE0OjE2OjIxLjE1MloiLDc1OTc1XQ==","node":{"id":"HVjXlAHaQYbtLw6YpHPHToYe7PwKFBMqaz5cJt55GbM","owner":{"address":"Shu_0sBFhXRcRcVXGiSE8IvduPRBnoPKK85IG3AKVAc"},"recipient":"","bundledIn":{"id":"rt8YCWKGL64hqeKsoXJlJwBtZgiYs2prLwDqVEU2qSM"},"tags":[{"name":"Content-Type","value":"application/octet-stream"},{"name":"Cipher","value":"AES256-GCM"},{"name":"Cipher-IV","value":"bLVTQJNW8zhpXkpj"},{"name":"ArFS","value":"0.11"},{"name":"Entity-Type","value":"file"},{"name":"Drive-Id","value":"07f88d70-4200-4404-86eb-056b72cb1b18"},{"name":"Parent-Folder-Id","value":"6b372496-8cd2-4b60-99bf-c8837c2d864d"},{"name":"File-Id","value":"7130317d-6068-4a5a-8c0c-ba545fd2d4cd"},{"name":"App-Name","value":"ArDrive-Web"},{"name":"App-Version","value":"1.14.0"},{"name":"Unix-Time","value":"1651720544"}],"data":{"size":"188","type":null},"quantity":{"winston":"0"},"fee":{"winston":"0"},"block":{"timestamp":1651721102,"height":927097}}},{"cursor":"WyIyMDIyLTA1LTE2VDE0OjE2OjIxLjE1MloiLDc1OTc2XQ==","node":{"id":"InAP65cCUYVHONYPqAmUrgRScraz_iFpfbYlLIxlTBE","owner":{"address":"Shu_0sBFhXRcRcVXGiSE8IvduPRBnoPKK85IG3AKVAc"},"recipient":"","bundledIn":{"id":"rt8YCWKGL64hqeKsoXJlJwBtZgiYs2prLwDqVEU2qSM"},"tags":[{"name":"Content-Type","value":"application/octet-stream"},{"name":"Cipher","value":"AES256-GCM"},{"name":"Cipher-IV","value":"2F-WKFTClFX3PLpk"},{"name":"App-Name","value":"ArDrive-Web"},{"name":"App-Version","value":"1.14.0"},{"name":"Unix-Time","value":"1651720536"}],"data":{"size":"38992163","type":null},"quantity":{"winston":"0"},"fee":{"winston":"0"},"block":{"timestamp":1651721102,"height":927097}}},{"cursor":"WyIyMDIyLTA1LTE2VDE0OjE2OjIxLjE1MloiLDc1OTc3XQ==","node":{"id":"jp8s8y3HYytu48g4doH8sOgTgosub-YvR2gy-mjqNCs","owner":{"address":"Shu_0sBFhXRcRcVXGiSE8IvduPRBnoPKK85IG3AKVAc"},"recipient":"","bundledIn":{"id":"rt8YCWKGL64hqeKsoXJlJwBtZgiYs2prLwDqVEU2qSM"},"tags":[{"name":"Content-Type","value":"application/octet-stream"},{"name":"Cipher","value":"AES256-GCM"},{"name":"Cipher-IV","value":"FVA05ukIrakmc3ii"},{"name":"ArFS","value":"0.11"},{"name":"Entity-Type","value":"file"},{"name":"Drive-Id","value":"07f88d70-4200-4404-86eb-056b72cb1b18"},{"name":"Parent-Folder-Id","value":"6b372496-8cd2-4b60-99bf-c8837c2d864d"},{"name":"File-Id","value":"48942787-4d4c-4e57-838d-39bcfa5e5cb0"},{"name":"App-Name","value":"ArDrive-Web"},{"name":"App-Version","value":"1.14.0"},{"name":"Unix-Time","value":"1651720544"}],"data":{"size":"188","type":null},"quantity":{"winston":"0"},"fee":{"winston":"0"},"block":{"timestamp":1651721102,"height":927097}}},{"cursor":"WyIyMDIyLTA1LTE2VDE0OjE2OjIxLjE1MloiLDc1OTc4XQ==","node":{"id":"nElnJ45SautCXEhpPdRJuTl2_7ggCjgHDh4N7MeFMbw","owner":{"address":"Shu_0sBFhXRcRcVXGiSE8IvduPRBnoPKK85IG3AKVAc"},"recipient":"","bundledIn":{"id":"rt8YCWKGL64hqeKsoXJlJwBtZgiYs2prLwDqVEU2qSM"},"tags":[{"name":"Content-Type","value":"application/octet-stream"},{"name":"Cipher","value":"AES256-GCM"},{"name":"Cipher-IV","value":"sQJESSnM9y-pMDEe"},{"name":"App-Name","value":"ArDrive-Web"},{"name":"App-Version","value":"1.14.0"},{"name":"Unix-Time","value":"1651720474"}],"data":{"size":"36436495","type":null},"quantity":{"winston":"0"},"fee":{"winston":"0"},"block":{"timestamp":1651721102,"height":927097}}},{"cursor":"WyIyMDIyLTA1LTE2VDE0OjE2OjIxLjE1MloiLDc1OTc5XQ==","node":{"id":"nwP3-MoWmkqdsAVtZPE7bB53t6eNDRlz6IlEA0VcFz4","owner":{"address":"Shu_0sBFhXRcRcVXGiSE8IvduPRBnoPKK85IG3AKVAc"},"recipient":"","bundledIn":{"id":"rt8YCWKGL64hqeKsoXJlJwBtZgiYs2prLwDqVEU2qSM"},"tags":[{"name":"Content-Type","value":"application/octet-stream"},{"name":"Cipher","value":"AES256-GCM"},{"name":"Cipher-IV","value":"PIBdsA1iBbvW4cGk"},{"name":"App-Name","value":"ArDrive-Web"},{"name":"App-Version","value":"1.14.0"},{"name":"Unix-Time","value":"1651720543"}],"data":{"size":"38977146","type":null},"quantity":{"winston":"0"},"fee":{"winston":"0"},"block":{"timestamp":1651721102,"height":927097}}},{"cursor":"WyIyMDIyLTA1LTE2VDE0OjE2OjIxLjE1MloiLDc1OTgwXQ==","node":{"id":"nYKcrWHT-mpu2FrEvoALwsDkkkA-WaSSn91j4sRTqOA","owner":{"address":"Shu_0sBFhXRcRcVXGiSE8IvduPRBnoPKK85IG3AKVAc"},"recipient":"","bundledIn":{"id":"rt8YCWKGL64hqeKsoXJlJwBtZgiYs2prLwDqVEU2qSM"},"tags":[{"name":"Content-Type","value":"application/octet-stream"},{"name":"Cipher","value":"AES256-GCM"},{"name":"Cipher-IV","value":"wHMkxLqCzb0A4gTO"},{"name":"App-Name","value":"ArDrive-Web"},{"name":"App-Version","value":"1.14.0"},{"name":"Unix-Time","value":"1651720487"}],"data":{"size":"36750079","type":null},"quantity":{"winston":"0"},"fee":{"winston":"0"},"block":{"timestamp":1651721102,"height":927097}}},{"cursor":"WyIyMDIyLTA1LTE2VDE0OjE2OjIxLjE1MloiLDc1OTgxXQ==","node":{"id":"PeNgYdPHJcgucG5mC7d4q9AaYViBzSzMnlKtAcESAK4","owner":{"address":"Shu_0sBFhXRcRcVXGiSE8IvduPRBnoPKK85IG3AKVAc"},"recipient":"","bundledIn":{"id":"rt8YCWKGL64hqeKsoXJlJwBtZgiYs2prLwDqVEU2qSM"},"tags":[{"name":"Content-Type","value":"application/octet-stream"},{"name":"Cipher","value":"AES256-GCM"},{"name":"Cipher-IV","value":"cIoCky0xGbKqvO4v"},{"name":"ArFS","value":"0.11"},{"name":"Entity-Type","value":"file"},{"name":"Drive-Id","value":"07f88d70-4200-4404-86eb-056b72cb1b18"},{"name":"Parent-Folder-Id","value":"6b372496-8cd2-4b60-99bf-c8837c2d864d"},{"name":"File-Id","value":"d6819fa3-e1d7-4076-805c-2bea86c5e42d"},{"name":"App-Name","value":"ArDrive-Web"},{"name":"App-Version","value":"1.14.0"},{"name":"Unix-Time","value":"1651720544"}],"data":{"size":"188","type":null},"quantity":{"winston":"0"},"fee":{"winston":"0"},"block":{"timestamp":1651721102,"height":927097}}},{"cursor":"WyIyMDIyLTA1LTE2VDE0OjE2OjIxLjE1MloiLDc1OTgyXQ==","node":{"id":"pp2NRHWjfqTdKhcyAhS0b3n6Gng7m8alvNaXcfsnV2E","owner":{"address":"Shu_0sBFhXRcRcVXGiSE8IvduPRBnoPKK85IG3AKVAc"},"recipient":"","bundledIn":{"id":"rt8YCWKGL64hqeKsoXJlJwBtZgiYs2prLwDqVEU2qSM"},"tags":[{"name":"Content-Type","value":"application/octet-stream"},{"name":"Cipher","value":"AES256-GCM"},{"name":"Cipher-IV","value":"LzQZSdWeUU2Dg-MI"},{"name":"ArFS","value":"0.11"},{"name":"Entity-Type","value":"file"},{"name":"Drive-Id","value":"07f88d70-4200-4404-86eb-056b72cb1b18"},{"name":"Parent-Folder-Id","value":"6b372496-8cd2-4b60-99bf-c8837c2d864d"},{"name":"File-Id","value":"46a59dcf-15a8-4b8f-a113-8ff6fa23c23f"},{"name":"App-Name","value":"ArDrive-Web"},{"name":"App-Version","value":"1.14.0"},{"name":"Unix-Time","value":"1651720544"}],"data":{"size":"188","type":null},"quantity":{"winston":"0"},"fee":{"winston":"0"},"block":{"timestamp":1651721102,"height":927097}}},{"cursor":"WyIyMDIyLTA1LTE2VDE0OjE2OjIxLjE1MloiLDc1OTgzXQ==","node":{"id":"-PrqbzB8oXhbwHZ5a_NTPZ8HsnPEDlaLYIhhmMuRvDA","owner":{"address":"Shu_0sBFhXRcRcVXGiSE8IvduPRBnoPKK85IG3AKVAc"},"recipient":"","bundledIn":{"id":"rt8YCWKGL64hqeKsoXJlJwBtZgiYs2prLwDqVEU2qSM"},"tags":[{"name":"Content-Type","value":"application/octet-stream"},{"name":"Cipher","value":"AES256-GCM"},{"name":"Cipher-IV","value":"8xKyHjiRkEa3kaLl"},{"name":"App-Name","value":"ArDrive-Web"},{"name":"App-Version","value":"1.14.0"},{"name":"Unix-Time","value":"1651720515"}],"data":{"size":"37154569","type":null},"quantity":{"winston":"0"},"fee":{"winston":"0"},"block":{"timestamp":1651721102,"height":927097}}},{"cursor":"WyIyMDIyLTA1LTE2VDE0OjE2OjIxLjE1MloiLDc1OTg0XQ==","node":{"id":"QRSMlnQvKz2EhDM0jA7u7PKMKn0s2z4mnZxZ80ZEpSM","owner":{"address":"Shu_0sBFhXRcRcVXGiSE8IvduPRBnoPKK85IG3AKVAc"},"recipient":"","bundledIn":{"id":"rt8YCWKGL64hqeKsoXJlJwBtZgiYs2prLwDqVEU2qSM"},"tags":[{"name":"Content-Type","value":"application/octet-stream"},{"name":"Cipher","value":"AES256-GCM"},{"name":"Cipher-IV","value":"z3fnxd6h2dzOIkXK"},{"name":"ArFS","value":"0.11"},{"name":"Entity-Type","value":"file"},{"name":"Drive-Id","value":"07f88d70-4200-4404-86eb-056b72cb1b18"},{"name":"Parent-Folder-Id","value":"6b372496-8cd2-4b60-99bf-c8837c2d864d"},{"name":"File-Id","value":"5b476be6-387c-472a-b69f-d6a63a0d376c"},{"name":"App-Name","value":"ArDrive-Web"},{"name":"App-Version","value":"1.14.0"},{"name":"Unix-Time","value":"1651720544"}],"data":{"size":"188","type":null},"quantity":{"winston":"0"},"fee":{"winston":"0"},"block":{"timestamp":1651721102,"height":927097}}},{"cursor":"WyIyMDIyLTA1LTE2VDE0OjE2OjIxLjE1MloiLDc1OTg1XQ==","node":{"id":"rt8YCWKGL64hqeKsoXJlJwBtZgiYs2prLwDqVEU2qSM","owner":{"address":"Shu_0sBFhXRcRcVXGiSE8IvduPRBnoPKK85IG3AKVAc"},"recipient":"Zznp65qgTIm2QBMjjoEaHKOmQrpTu0tfOcdbkm_qoL4","bundledIn":null,"tags":[{"name":"Bundle-Format","value":"binary"},{"name":"Bundle-Version","value":"2.0.0"},{"name":"App-Name","value":"ArDrive-Web"},{"name":"App-Version","value":"1.14.0"},{"name":"Unix-Time","value":"1651720544"},{"name":"Tip-Type","value":"data upload"}],"data":{"size":"375379616","type":null},"quantity":{"winston":"13108738156"},"fee":{"winston":"87391587710"},"block":{"timestamp":1651721102,"height":927097}}},{"cursor":"WyIyMDIyLTA1LTE2VDE0OjE2OjIxLjE1MloiLDc1OTg2XQ==","node":{"id":"tjW0FkDFSomK_rIk_iK-p7twcXNHxEAxJ_7ZZ3ka7TM","owner":{"address":"Shu_0sBFhXRcRcVXGiSE8IvduPRBnoPKK85IG3AKVAc"},"recipient":"","bundledIn":{"id":"rt8YCWKGL64hqeKsoXJlJwBtZgiYs2prLwDqVEU2qSM"},"tags":[{"name":"Content-Type","value":"application/octet-stream"},{"name":"Cipher","value":"AES256-GCM"},{"name":"Cipher-IV","value":"3JQ1Kt2Bu_fLc_ah"},{"name":"App-Name","value":"ArDrive-Web"},{"name":"App-Version","value":"1.14.0"},{"name":"Unix-Time","value":"1651720494"}],"data":{"size":"36985576","type":null},"quantity":{"winston":"0"},"fee":{"winston":"0"},"block":{"timestamp":1651721102,"height":927097}}},{"cursor":"WyIyMDIyLTA1LTE2VDE0OjE2OjIxLjE1MloiLDc1OTg3XQ==","node":{"id":"vfrTakG4fDMGNffIKywdLgGF7DEE2TdvJqS1bBXhqa8","owner":{"address":"Shu_0sBFhXRcRcVXGiSE8IvduPRBnoPKK85IG3AKVAc"},"recipient":"","bundledIn":{"id":"rt8YCWKGL64hqeKsoXJlJwBtZgiYs2prLwDqVEU2qSM"},"tags":[{"name":"Content-Type","value":"application/octet-stream"},{"name":"Cipher","value":"AES256-GCM"},{"name":"Cipher-IV","value":"TZU9ShhYDPZw2buo"},{"name":"ArFS","value":"0.11"},{"name":"Entity-Type","value":"file"},{"name":"Drive-Id","value":"07f88d70-4200-4404-86eb-056b72cb1b18"},{"name":"Parent-Folder-Id","value":"6b372496-8cd2-4b60-99bf-c8837c2d864d"},{"name":"File-Id","value":"4b9c81a7-ff93-4a75-af86-9caa8394aca2"},{"name":"App-Name","value":"ArDrive-Web"},{"name":"App-Version","value":"1.14.0"},{"name":"Unix-Time","value":"1651720544"}],"data":{"size":"188","type":null},"quantity":{"winston":"0"},"fee":{"winston":"0"},"block":{"timestamp":1651721102,"height":927097}}},{"cursor":"WyIyMDIyLTA1LTE2VDE0OjE2OjIxLjE1MloiLDc1OTg4XQ==","node":{"id":"x09OGzsSavFnhDHqvY4VYb7O1hhgJ2LSKeTGjShSWKs","owner":{"address":"Shu_0sBFhXRcRcVXGiSE8IvduPRBnoPKK85IG3AKVAc"},"recipient":"","bundledIn":{"id":"rt8YCWKGL64hqeKsoXJlJwBtZgiYs2prLwDqVEU2qSM"},"tags":[{"name":"Content-Type","value":"application/octet-stream"},{"name":"Cipher","value":"AES256-GCM"},{"name":"Cipher-IV","value":"Yk2UyDxV6iB5VrG4"},{"name":"App-Name","value":"ArDrive-Web"},{"name":"App-Version","value":"1.14.0"},{"name":"Unix-Time","value":"1651720529"}],"data":{"size":"38852294","type":null},"quantity":{"winston":"0"},"fee":{"winston":"0"},"block":{"timestamp":1651721102,"height":927097}}},{"cursor":"WyIyMDIyLTA1LTE2VDE0OjE2OjIxLjE1MloiLDc1OTg5XQ==","node":{"id":"xeCUTVNXbT2rneFIR26wbUld79Id5uEgduy44y_HzCM","owner":{"address":"Shu_0sBFhXRcRcVXGiSE8IvduPRBnoPKK85IG3AKVAc"},"recipient":"","bundledIn":{"id":"rt8YCWKGL64hqeKsoXJlJwBtZgiYs2prLwDqVEU2qSM"},"tags":[{"name":"Content-Type","value":"application/octet-stream"},{"name":"Cipher","value":"AES256-GCM"},{"name":"Cipher-IV","value":"yh0n4stxjTaZTOiR"},{"name":"ArFS","value":"0.11"},{"name":"Entity-Type","value":"file"},{"name":"Drive-Id","value":"07f88d70-4200-4404-86eb-056b72cb1b18"},{"name":"Parent-Folder-Id","value":"6b372496-8cd2-4b60-99bf-c8837c2d864d"},{"name":"File-Id","value":"f762323b-c657-436d-85e3-fbaef5f3aef9"},{"name":"App-Name","value":"ArDrive-Web"},{"name":"App-Version","value":"1.14.0"},{"name":"Unix-Time","value":"1651720544"}],"data":{"size":"188","type":null},"quantity":{"winston":"0"},"fee":{"winston":"0"},"block":{"timestamp":1651721102,"height":927097}}},{"cursor":"WyIyMDIyLTA1LTE2VDE0OjE2OjIxLjE1MloiLDc1OTkwXQ==","node":{"id":"--xnOnR8Pbidktxkp_Of1yp_5n5WGDEcH5QdmHZn1qM","owner":{"address":"Shu_0sBFhXRcRcVXGiSE8IvduPRBnoPKK85IG3AKVAc"},"recipient":"","bundledIn":{"id":"rt8YCWKGL64hqeKsoXJlJwBtZgiYs2prLwDqVEU2qSM"},"tags":[{"name":"Content-Type","value":"application/octet-stream"},{"name":"Cipher","value":"AES256-GCM"},{"name":"Cipher-IV","value":"35mBHi04lupvigj_"},{"name":"App-Name","value":"ArDrive-Web"},{"name":"App-Version","value":"1.14.0"},{"name":"Unix-Time","value":"1651720501"}],"data":{"size":"37040434","type":null},"quantity":{"winston":"0"},"fee":{"winston":"0"},"block":{"timestamp":1651721102,"height":927097}}},{"cursor":"WyIyMDIyLTA1LTE2VDE0OjE2OjIxLjE1MloiLDc1OTkxXQ==","node":{"id":"ZgjwnO641g8iYdtYZ6P_m5SQviRyKosLd72z0i9_uag","owner":{"address":"Shu_0sBFhXRcRcVXGiSE8IvduPRBnoPKK85IG3AKVAc"},"recipient":"","bundledIn":{"id":"rt8YCWKGL64hqeKsoXJlJwBtZgiYs2prLwDqVEU2qSM"},"tags":[{"name":"Content-Type","value":"application/octet-stream"},{"name":"Cipher","value":"AES256-GCM"},{"name":"Cipher-IV","value":"m6vIMA2LeRPvxKnL"},{"name":"ArFS","value":"0.11"},{"name":"Entity-Type","value":"file"},{"name":"Drive-Id","value":"07f88d70-4200-4404-86eb-056b72cb1b18"},{"name":"Parent-Folder-Id","value":"6b372496-8cd2-4b60-99bf-c8837c2d864d"},{"name":"File-Id","value":"062d91bc-ffdb-4c06-8b48-10ffc5071c8e"},{"name":"App-Name","value":"ArDrive-Web"},{"name":"App-Version","value":"1.14.0"},{"name":"Unix-Time","value":"1651720544"}],"data":{"size":"188","type":null},"quantity":{"winston":"0"},"fee":{"winston":"0"},"block":{"timestamp":1651721102,"height":927097}}}]