[{"cursor":"WyIyMDIyLTA1LTE5VDIwOjU1OjQwLjA0NVoiLDU5M10=","node":{"id":"73QjjPD1BE1-TO-nCdPvcZRo10G4_ri-3XEWls4Cj_A","owner":{"address":"5_PIU3CMeKaT12WUg0Q4BjBPf4EvusIrzCVD9u7kMKY"},"recipient":"","bundledIn":{"id":"T8B-KdMqNE40w8D9-Kf1_f7ir3IgWr5SIDvJ7fq-Bq0"},"tags":[{"name":"Content-Type","value":"application/octet-stream"},{"name":"Cipher","value":"AES256-GCM"},{"name":"Cipher-IV","value":"ffLsuy5oupLxoUgG"},{"name":"ArFS","value":"0.11"},{"name":"Entity-Type","value":"drive"},{"name":"Drive-Id","value":"a92b149f-a20c-4863-b1c1-f30b5db10d17"},{"name":"Drive-Privacy","value":"private"},{"name":"Drive-Auth-Mode","value":"password"},{"name":"App-Name","value":"ArDrive-Web"},{"name":"App-Version","value":"1.17.0"},{"name":"Unix-Time","value":"1652930495"}],"data":{"size":"89","type":null},"quantity":{"winston":"0"},"fee":{"winston":"0"},"block":{"timestamp":1652930868,"height":936579}}},{"cursor":"WyIyMDIyLTA1LTE5VDIwOjU1OjQwLjA0NVoiLDU5NF0=","node":{"id":"LWOkN-RV2coIlQoV4teRMR7hY25TqP7TvbEJNa5z97w","owner":{"address":"5_PIU3CMeKaT12WUg0Q4BjBPf4EvusIrzCVD9u7kMKY"},"recipient":"","bundledIn":{"id":"T8B-KdMqNE40w8D9-Kf1_f7ir3IgWr5SIDvJ7fq-Bq0"},"tags":[{"name":"Content-Type","value":"application/octet-stream"},{"name":"Cipher","value":"AES256-GCM"},{"name":"Cipher-IV","value":"fZuwxvdOf9hPZVor"},{"name":"ArFS","value":"0.11"},{"name":"Entity-Type","value":"folder"},{"name":"Drive-Id","value":"a92b149f-a20c-4863-b1c1-f30b5db10d17"},{"name":"Folder-Id","value":"4e4a6f30-af2c-4cd0-b8b8-930d5393776d"},{"name":"App-Name","value":"ArDrive-Web"},{"name":"App-Version","value":"1.17.0"},{"name":"Unix-Time","value":"1652930495"}],"data":{"size":"35","type":null},"quantity":{"winston":"0"},"fee":{"winston":"0"},"block":{"timestamp":1652930868,"height":936579}}},{"cursor":"WyIyMDIyLTA1LTE5VDIwOjU1OjQwLjA0NVoiLDU5NV0=","node":{"id":"T8B-KdMqNE40w8D9-Kf1_f7ir3IgWr5SIDvJ7fq-Bq0","owner":{"address":"5_PIU3CMeKaT12WUg0Q4BjBPf4EvusIrzCVD9u7kMKY"},"recipient":"","bundledIn":null,"tags":[{"name":"Bundle-Format","value":"binary"},{"name":"Bundle-Version","value":"2.0.0"},{"name":"App-Name","value":"ArDrive-Web"},{"name":"App-Version","value":"1.17.0"},{"name":"Unix-Time","value":"1652930495"}],"data":{"size":"2907","type":null},"quantity":{"winston":"0"},"fee":{"winston":"72600854"},"block":{"timestamp":1652930868,"height":936579}}}]