[{"cursor":"WyIyMDIyLTA1LTE2VDE0OjE2OjIxLjE1MloiLDgzNTEzXQ==","node":{"id":"6PzcwtJhTSyqG7jwhbJX3qN6acld0y_pT60F5uf0J2w","owner":{"address":"KFgG-LzRV6NHeXEFqkOIspPCdaxkjHickQFDQnhQIAI"},"recipient":"","bundledIn":{"id":"HZwCFW49cbS5PRxvmNFN-_I1hVtUCZ7AexPr2btgk60"},"tags":[{"name":"Content-Type","value":"application/octet-stream"},{"name":"Cipher","value":"AES256-GCM"},{"name":"Cipher-IV","value":"ct8yKV7R_JtadPcU"},{"name":"ArFS","value":"0.11"},{"name":"Entity-Type","value":"file"},{"name":"Drive-Id","value":"600b9b3a-1ff1-40f9-9f7b-e33fd7fd540a"},{"name":"Parent-Folder-Id","value":"d6078e9a-67f7-47b9-9ff4-a7413dde89c0"},{"name":"File-Id","value":"49a1689f-e989-4eff-90cb-8e1600658d71"},{"name":"App-Name","value":"ArDrive-Web"},{"name":"App-Version","value":"1.13.0"},{"name":"Unix-Time","value":"1651574463"}],"data":{"size":"172","type":null},"quantity":{"winston":"0"},"fee":{"winston":"0"},"block":{"timestamp":1651574945,"height":925941}}},{"cursor":"WyIyMDIyLTA1LTE2VDE0OjE2OjIxLjE1MloiLDgzNTE0XQ==","node":{"id":"HZwCFW49cbS5PRxvmNFN-_I1hVtUCZ7AexPr2btgk60","owner":{"address":"KFgG-LzRV6NHeXEFqkOIspPCdaxkjHickQFDQnhQIAI"},"recipient":"Zznp65qgTIm2QBMjjoEaHKOmQrpTu0tfOcdbkm_qoL4","bundledIn":null,"tags":[{"name":"Bundle-Format","value":"binary"},{"name":"Bundle-Version","value":"2.0.0"},{"name":"App-Name","value":"ArDrive-Web"},{"name":"App-Version","value":"1.13.0"},{"name":"Unix-Time","value":"1651574463"},{"name":"Tip-Type","value":"data upload"}],"data":{"size":"2913","type":null},"quantity":{"winston":"9266161"},"fee":{"winston":"61774411"},"block":{"timestamp":1651574945,"height":925941}}},{"cursor":"WyIyMDIyLTA1LTE2VDE0OjE2OjIxLjE1MloiLDgzNTE1XQ==","node":{"id":"XsEAmYs1Dp-SW06Hm84Qes_PPioADpmuTXI_DkaX8lI","owner":{"address":"KFgG-LzRV6NHeXEFqkOIspPCdaxkjHickQFDQnhQIAI"},"recipient":"","bundledIn":{"id":"HZwCFW49cbS5PRxvmNFN-_I1hVtUCZ7AexPr2btgk60"},"tags":[{"name":"Content-Type","value":"application/octet-stream"},{"name":"Cipher","value":"AES256-GCM"},{"name":"Cipher-IV","value":"STqD8dJiLmAXtPVn"},{"name":"App-Name","value":"ArDrive-Web"},{"name":"App-Version","value":"1.13.0"},{"name":"Unix-Time","value":"1651574463"}],"data":{"size":"29","type":null},"quantity":{"winston":"0"},"fee":{"winston":"0"},"block":{"timestamp":1651574945,"height":925941}}}]