[{"cursor":"WyIyMDIyLTA1LTE2VDE0OjE2OjIxLjE1MloiLDgzNTI0XQ==","node":{"id":"o28Jz1IPBHBDM0IJ5Fnw2UjaCc4CTm68EGTJ-udYtpU","owner":{"address":"iU_fpcxaWFCeTxVXfsGm1ZP1qIaUHfHsFKp1Y7G9JQ8"},"recipient":"","bundledIn":null,"tags":[{"name":"Content-Type","value":"application/json"},{"name":"ArFS","value":"0.11"},{"name":"Entity-Type","value":"drive"},{"name":"Drive-Id","value":"a127dd3e-dc6b-4e56-be3b-0331e9db0392"},{"name":"Drive-Privacy","value":"public"},{"name":"App-Name","value":"ArDrive-Web"},{"name":"App-Version","value":"1.13.0"},{"name":"Unix-Time","value":"1651560813"}],"data":{"size":"75","type":"application/json"},"quantity":{"winston":"0"},"fee":{"winston":"61774411"},"block":{"timestamp":1651561973,"height":925835}}}]